{
  "name": "bpg-phone-sans",
  "description": "BPG Phone Sans Web-Font Package",
  "version": "1.0.0",
  "keywords": [
    "ttf",
    "woff",
    "woff2",
    "svg",
    "font",
    "web-font",
    "bpg-phone-sans"
  ],
  "main": [
    "css/bpg-phone-sans.css"
  ],
  "homepage": "https://github.com/web-fonts/bpg-phone-sans",
  "authors": [
    "Lado Lomidze <lado.lomidze@gmail.com>"
  ],
  "repository": {
    "type": "git",
    "url": "https://github.com/web-fonts/bpg-phone-sans.git"
  },
  "license": [
    "MIT",
    "CC-BY-NC-ND-4.0"
  ],
  "ignore": [
    "**/.*",
    "node_modules",
    "bower_components",
    "test",
    "tests",
    "*.md",
    "font.json"
  ],
  "_release": "1.0.0",
  "_resolution": {
    "type": "version",
    "tag": "1.0.0",
    "commit": "d818d6262a6d7eb9428ded775533f7d7fd4276f9"
  },
  "_source": "git://github.com/web-fonts/bpg-phone-sans.git",
  "_target": "~1.0.0",
  "_originalSource": "bpg-phone-sans"
}